sop/__init__.py
sop/elements.py
sop/mailhog.py
sop/odoo/__init__.py
sop/odoo/accounting.py
sop/odoo/dialogs.py
sop/odoo/elements.py
sop/odoo/sales.py
sop/odoo/terms.py
sop/odoo/views.py
sop/testing/__init__.py
sop/testing/conftest.py
selenium_odoo_pages-0.4.0.dist-info/LICENSE
selenium_odoo_pages-0.4.0.dist-info/METADATA
selenium_odoo_pages-0.4.0.dist-info/WHEEL
selenium_odoo_pages-0.4.0.dist-info/entry_points.txt
selenium_odoo_pages-0.4.0.dist-info/top_level.txt
selenium_odoo_pages-0.4.0.dist-info/RECORD
