Metadata-Version: 2.1
Name: selenium-odoo-pages
Version: 0.4.0
Summary: A set of pages and elements used to interact with odoo pages and widget using the page selenium objects pattern
Home-page: https://gitlab.com/micro-entreprise/selenium-odoo-pages
Author: Pierre Verkest
Author-email: pierreverkest84@gmail.com
License: UNKNOWN
Platform: UNKNOWN
Classifier: Development Status :: 4 - Beta
Classifier: License :: OSI Approved :: Apache Software License
Classifier: Programming Language :: Python :: 3
Requires-Dist: selenium (<4)
Requires-Dist: selenium-configurator
Requires-Dist: python-dotenv
Requires-Dist: pytest-bdd
